m365_roadmap_mcp/__init__.py
m365_roadmap_mcp/__main__.py
m365_roadmap_mcp/server.py
m365_roadmap_mcp/feeds/__init__.py
m365_roadmap_mcp/feeds/m365_api.py
m365_roadmap_mcp/models/__init__.py
m365_roadmap_mcp/models/feature.py
m365_roadmap_mcp/tools/__init__.py
m365_roadmap_mcp/tools/search.py
m365_roadmap_mcp-0.2.1.dist-info/METADATA
m365_roadmap_mcp-0.2.1.dist-info/WHEEL
m365_roadmap_mcp-0.2.1.dist-info/entry_points.txt
m365_roadmap_mcp-0.2.1.dist-info/licenses/LICENSE
m365_roadmap_mcp-0.2.1.dist-info/RECORD
