Metadata-Version: 2.4
Name: m365-roadmap-mcp
Version: 0.2.1
Summary: MCP server for querying the Microsoft 365 Roadmap
Project-URL: Homepage, https://github.com/jonnybottles/M365-roadmap-mcp-server
Project-URL: Repository, https://github.com/jonnybottles/M365-roadmap-mcp-server
Project-URL: Issues, https://github.com/jonnybottles/M365-roadmap-mcp-server/issues
Author: Justin Buttler
License-Expression: MIT
License-File: LICENSE
Keywords: ai-agent,gcc,mcp,microsoft-365,roadmap
Classifier: Development Status :: 4 - Beta
Classifier: License :: OSI Approved :: MIT License
Classifier: Programming Language :: Python :: 3
Classifier: Programming Language :: Python :: 3.11
Classifier: Programming Language :: Python :: 3.12
Classifier: Programming Language :: Python :: 3.13
Requires-Python: >=3.11
Requires-Dist: fastmcp
Requires-Dist: httpx
Requires-Dist: pydantic
Provides-Extra: dev
Requires-Dist: pytest; extra == 'dev'
Requires-Dist: pytest-asyncio; extra == 'dev'
